setup.cfg
setup.py
sjwt/__init__.py
sjwt/models.py
sjwt/sjwt.py
sjwt.egg-info/PKG-INFO
sjwt.egg-info/SOURCES.txt
sjwt.egg-info/dependency_links.txt
sjwt.egg-info/not-zip-safe
sjwt.egg-info/top_level.txt