Metadata-Version: 2.1
Name: sjwt
Version: 0.2.3
Summary: Generate, check token, and get payload from token
Author-email: sagrityanin4@gmail.com
